{
  "mode": "pre",
  "tag": "alpha",
  "initialVersions": {
    "@apollo/server-integration-testsuite": "3.6.7",
    "@apollo/server-plugin-response-cache": "3.6.7",
    "@apollo/server": "3.6.7",
    "@apollo/usage-reporting-protobuf": "3.3.1",
    "@apollo/server-plugin-landing-page-graphql-playground": "3.0.0"
  },
  "changesets": [
    "blue-bottles-jump",
    "chatty-baboons-search",
    "chilled-cows-drum",
    "eleven-drinks-mix",
    "eleven-needles-collect",
    "empty-peaches-heal",
    "famous-parents-argue",
    "fifty-peaches-bathe",
    "gorgeous-penguins-jog",
    "healthy-glasses-reflect",
    "hip-cheetahs-fail",
    "lazy-emus-hunt",
    "many-plums-smile",
    "neat-buckets-marry",
    "ninety-panthers-accept",
    "ninety-tips-unite",
    "old-insects-smash",
    "old-papayas-switch",
    "pink-eggs-draw",
    "quick-beans-applaud",
    "shaggy-badgers-act",
    "shaggy-schools-sparkle",
    "short-lies-kneel",
    "silly-icons-taste",
    "six-pianos-refuse",
    "sixty-flowers-press",
    "small-cycles-hammer",
    "small-suits-compare",
    "spicy-lions-deliver",
    "spicy-pugs-deliver",
    "spotty-days-eat",
    "stale-goats-serve",
    "stale-sheep-search",
    "thirty-donkeys-sing",
    "twenty-cooks-repair",
    "violet-mayflies-help",
    "wet-kiwis-play",
    "wet-rats-shake",
    "witty-squids-vanish"
  ]
}
